setup.py
django_scrup.egg-info/PKG-INFO
django_scrup.egg-info/SOURCES.txt
django_scrup.egg-info/dependency_links.txt
django_scrup.egg-info/requires.txt
django_scrup.egg-info/top_level.txt
scrup/__init__.py
scrup/models.py
scrup/tests.py
scrup/urls.py
scrup/utils.py
scrup/views.py