Metadata-Version: 1.0
Name: django-scrup
Version: 0.1
Summary: A django-based web receiver for Scrup which stores screencaptures on S3.
Home-page: http://github.com/idangazit/django-scrup
Author: Idan Gazit
Author-email: idan@pixane.com
License: UNKNOWN
Platform: UNKNOWN
Classifier: Development Status :: 3 - Alpha
Classifier: Environment :: Web Environment
Classifier: Intended Audience :: Developers
Classifier: License :: OSI Approved :: BSD License
Classifier: Operating System :: OS Independent
Classifier: Programming Language :: Python
Classifier: Framework :: Django
